{"eventType": "START", "eventTime": "2023-03-05T18:07:48.791023Z", "run": {"runId": "f99055dc-6368-4b2a-ae06-d21cdf444542"}, "inputs": [{"namespace": "meltano", "name": "flow_runs", "facets": {"schema": {"fields": {"id": {"type": "string"}, "created": {"type": "string"}, "updated": {"type": "string"}, "name": {"type": "string"}, "flow_id": {"type": "string"}, "state_id": {"type": "string"}, "deployment_id": {"type": ["null", "string"]}, "work_queue_name": {"type": ["null", "string"]}, "flow_version": {"type": ["null", "string"]}, "parameters": {"type": "object"}, "idempotency_key": {"type": ["null", "string"]}, "context": {"type": "object"}, "empirical_policy": {"type": "object"}, "tags": {"type": "array"}, "parent_task_run_id": {"type": ["null", "string"]}, "state_type": {"type": "string"}, "state_name": {"type": "string"}, "run_count": {"type": "integer"}, "expected_start_time": {"type": "string"}, "next_scheduled_start_time": {"type": ["null", "string"]}, "start_time": {"type": ["null", "string"]}, "end_time": {"type": ["null", "string"]}, "total_run_time": {"type": "number"}, "estimated_run_time": {"type": "number"}, "estimated_start_time_delta": {"type": "number"}, "auto_scheduled": {"type": "boolean"}, "infrastructure_document_id": {"type": ["null", "string"]}, "infrastructure_pid": {"type": ["null", "string"]}, "created_by": {"type": "object"}, "work_pool_name": {"type": ["null", "string"]}, "state": {"type": "object"}}}, "config": {}}}, {"namespace": "meltano", "name": "task_runs", "facets": {"schema": {"fields": {"id": {"type": "string"}, "created": {"type": "string"}, "updated": {"type": "string"}, "name": {"type": "string"}, "flow_id": {"type": "string"}, "state_id": {"type": "string"}, "deployment_id": {"type": "string"}, "work_queue_name": {"type": "string"}, "flow_version": {"type": "string"}, "parameters": {"type": "object"}, "idempotency_key": {"type": "string"}, "context": {"type": "object"}, "empirical_policy": {"type": "object"}, "tags": {"type": "array"}, "parent_task_run_id": {"type": "string"}, "state_type": {"type": "string"}, "state_name": {"type": "string"}, "run_count": {"type": "integer"}, "expected_start_time": {"type": "string"}, "next_scheduled_start_time": {"type": ["null", "string"]}, "start_time": {"type": "string"}, "end_time": {"type": "string"}, "total_run_time": {"type": "number"}, "estimated_run_time": {"type": "number"}, "estimated_start_time_delta": {"type": ["null", "number"]}, "auto_scheduled": {"type": "boolean"}, "infrastructure_document_id": {"type": "string"}, "infrastructure_pid": {"type": "string"}, "created_by": {"type": "object"}, "work_pool_name": {"type": "string"}, "state": {"type": "object"}}}, "config": {}}}], "outputs": []}
{"eventType": "COMPLETE", "eventTime": "2023-03-12T13:29:48.589527Z", "run": {"runId": "f99055dc-6368-4b2a-ae06-d21cdf444542", "metrics": {"http_request_duration": 272.59145900000044, "http_request_count": 1161, "sync_duration": 426.06621408462524, "record_count": 1665}}, "inputs": [{"namespace": "meltano", "name": "flow_runs", "facets": {"schema": {"fields": {"id": {"type": "string"}, "created": {"type": "string"}, "updated": {"type": "string"}, "name": {"type": "string"}, "flow_id": {"type": "string"}, "state_id": {"type": "string"}, "deployment_id": {"type": ["null", "string"]}, "work_queue_name": {"type": ["null", "string"]}, "flow_version": {"type": ["null", "string"]}, "parameters": {"type": "object"}, "idempotency_key": {"type": ["null", "string"]}, "context": {"type": "object"}, "empirical_policy": {"type": "object"}, "tags": {"type": "array"}, "parent_task_run_id": {"type": ["null", "string"]}, "state_type": {"type": "string"}, "state_name": {"type": "string"}, "run_count": {"type": "integer"}, "expected_start_time": {"type": "string"}, "next_scheduled_start_time": {"type": ["null", "string"]}, "start_time": {"type": ["null", "string"]}, "end_time": {"type": ["null", "string"]}, "total_run_time": {"type": "number"}, "estimated_run_time": {"type": "number"}, "estimated_start_time_delta": {"type": "number"}, "auto_scheduled": {"type": "boolean"}, "infrastructure_document_id": {"type": ["null", "string"]}, "infrastructure_pid": {"type": ["null", "string"]}, "created_by": {"type": "object"}, "work_pool_name": {"type": ["null", "string"]}, "state": {"type": "object"}}}, "config": {}}}, {"namespace": "meltano", "name": "task_runs", "facets": {"schema": {"fields": {"id": {"type": "string"}, "created": {"type": "string"}, "updated": {"type": "string"}, "name": {"type": "string"}, "flow_id": {"type": "string"}, "state_id": {"type": "string"}, "deployment_id": {"type": "string"}, "work_queue_name": {"type": "string"}, "flow_version": {"type": "string"}, "parameters": {"type": "object"}, "idempotency_key": {"type": "string"}, "context": {"type": "object"}, "empirical_policy": {"type": "object"}, "tags": {"type": "array"}, "parent_task_run_id": {"type": "string"}, "state_type": {"type": "string"}, "state_name": {"type": "string"}, "run_count": {"type": "integer"}, "expected_start_time": {"type": "string"}, "next_scheduled_start_time": {"type": ["null", "string"]}, "start_time": {"type": "string"}, "end_time": {"type": "string"}, "total_run_time": {"type": "number"}, "estimated_run_time": {"type": "number"}, "estimated_start_time_delta": {"type": ["null", "number"]}, "auto_scheduled": {"type": "boolean"}, "infrastructure_document_id": {"type": "string"}, "infrastructure_pid": {"type": "string"}, "created_by": {"type": "object"}, "work_pool_name": {"type": "string"}, "state": {"type": "object"}}}, "config": {}}}], "outputs": []}
